casar_lammps_mixin/__init__.py
casar_lammps_mixin/data_file_utils/angles_section.py
casar_lammps_mixin/data_file_utils/atoms_section.py
casar_lammps_mixin/data_file_utils/bonds_section.py
casar_lammps_mixin/data_file_utils/cs_info_section.py
casar_lammps_mixin/data_file_utils/header_section.py
casar_lammps_mixin/data_file_utils/masses_section.py
casar_lammps_mixin/data_file_utils/section_line.py
casar_lammps_mixin/data_types.py
casar_lammps_mixin/dump_handler.py
casar_lammps_mixin/lammps_data.py
casar_lammps_mixin/pbc_construct.py
casar_lammps_mixin/section_generator/angles.py
casar_lammps_mixin/section_generator/bonds.py
casar_lammps_mixin-0.2.0.dist-info/METADATA
casar_lammps_mixin-0.2.0.dist-info/WHEEL
casar_lammps_mixin-0.2.0.dist-info/RECORD
