Metadata-Version: 2.1
Name: casar-lammps-mixin
Version: 0.2.0
Summary: 
Author: Gabrielle Anne Sblendorio
Author-email: glsblendorio@gmail.com
Requires-Python: ==3.9.18
Classifier: Programming Language :: Python :: 3
Requires-Dist: dataclasses-json (>=0.6.3,<0.7.0)
Requires-Dist: matplotlib (>=3.8.0,<4.0.0)
Requires-Dist: numpy (>=1.26.0,<2.0.0)
Requires-Dist: pandas (>=2.1.1,<3.0.0)
Requires-Dist: parse (>=1.19.1,<2.0.0)
Requires-Dist: scikit-learn (>=1.3.1,<2.0.0)
